verilog/verilog_sim/05_fifo/src/async_fifo.v
`timescale 1ns / 1ps

module async_fifo #(
    parameter DATA_WIDTH = 8,
    parameter ADDR_WIDTH = 4
)(
    input  wire                  wr_clk,
    input  wire                  wr_rst_n,
    input  wire                  wr_en,
    input  wire [DATA_WIDTH-1:0] wr_data,
    output wire                  full,

    input  wire                  rd_clk,
    input  wire                  rd_rst_n,
    input  wire                  rd_en,
    output reg  [DATA_WIDTH-1:0] rd_data,
    output wire                  empty
);

localparam DEPTH = 1 << ADDR_WIDTH;

reg [DATA_WIDTH-1:0] mem [0:DEPTH-1];

reg [ADDR_WIDTH:0] wr_bin;
reg [ADDR_WIDTH:0] rd_bin;

reg [ADDR_WIDTH:0] wr_gray;
reg [ADDR_WIDTH:0] rd_gray;

reg [ADDR_WIDTH:0] wr_gray_sync1, wr_gray_sync2;
reg [ADDR_WIDTH:0] rd_gray_sync1, rd_gray_sync2;

wire [ADDR_WIDTH:0] wr_bin_next;
wire [ADDR_WIDTH:0] rd_bin_next;

wire [ADDR_WIDTH:0] wr_gray_next;
wire [ADDR_WIDTH:0] rd_gray_next;

assign wr_bin_next  = wr_bin + ((wr_en && !full) ? 1'b1 : 1'b0);
assign rd_bin_next  = rd_bin + ((rd_en && !empty) ? 1'b1 : 1'b0);

assign wr_gray_next = (wr_bin_next >> 1) ^ wr_bin_next;
assign rd_gray_next = (rd_bin_next >> 1) ^ rd_bin_next;

/*
    写指针逻辑
*/
always @(posedge wr_clk or negedge wr_rst_n) begin
    if (!wr_rst_n) begin
        wr_bin  <= 0;
        wr_gray <= 0;
    end else begin
        wr_bin  <= wr_bin_next;
        wr_gray <= wr_gray_next;

        if (wr_en && !full) begin
            mem[wr_bin[ADDR_WIDTH-1:0]] <= wr_data;
        end
    end
end

/*
    读指针逻辑
*/
always @(posedge rd_clk or negedge rd_rst_n) begin
    if (!rd_rst_n) begin
        rd_bin  <= 0;
        rd_gray <= 0;
        rd_data <= 0;
    end else begin
        rd_bin  <= rd_bin_next;
        rd_gray <= rd_gray_next;

        if (rd_en && !empty) begin
            rd_data <= mem[rd_bin[ADDR_WIDTH-1:0]];
        end
    end
end

/*
    写指针同步到读时钟域
*/
always @(posedge rd_clk or negedge rd_rst_n) begin
    if (!rd_rst_n) begin
        wr_gray_sync1 <= 0;
        wr_gray_sync2 <= 0;
    end else begin
        wr_gray_sync1 <= wr_gray;
        wr_gray_sync2 <= wr_gray_sync1;
    end
end

/*
    读指针同步到写时钟域
*/
always @(posedge wr_clk or negedge wr_rst_n) begin
    if (!wr_rst_n) begin
        rd_gray_sync1 <= 0;
        rd_gray_sync2 <= 0;
    end else begin
        rd_gray_sync1 <= rd_gray;
        rd_gray_sync2 <= rd_gray_sync1;
    end
end

/*
    empty 判断：
    读指针 == 同步过来的写指针
*/
assign empty = (rd_gray_next == wr_gray_sync2);

/*
    full 判断：
    写指针即将追上读指针一圈
*/
assign full = (wr_gray_next == {
    ~rd_gray_sync2[ADDR_WIDTH:ADDR_WIDTH-1],
     rd_gray_sync2[ADDR_WIDTH-2:0]
});


endmodule

verilog/verilog_sim/05_fifo/tb/tb_async_fifo.v
`timescale 1ns / 1ps

module tb_async_fifo;

parameter DATA_WIDTH = 8;
parameter ADDR_WIDTH = 8;

reg wr_clk;
reg rd_clk;
reg wr_rst_n;
reg rd_rst_n;

reg wr_en;
reg [DATA_WIDTH-1:0] wr_data;
wire full;

reg rd_en;
wire [DATA_WIDTH-1:0] rd_data;
wire empty;

async_fifo #(
    .DATA_WIDTH(DATA_WIDTH),
    .ADDR_WIDTH(ADDR_WIDTH)
) u_fifo (
    .wr_clk   (wr_clk),
    .wr_rst_n (wr_rst_n),
    .wr_en    (wr_en),
    .wr_data  (wr_data),
    .full     (full),

    .rd_clk   (rd_clk),
    .rd_rst_n (rd_rst_n),
    .rd_en    (rd_en),
    .rd_data  (rd_data),
    .empty    (empty)
);


    /*
        写时钟：10ns 周期
    */
    initial begin
        wr_clk = 0;
        forever #5 wr_clk = ~wr_clk;
    end

    /*
        读时钟：14ns 周期
    */
    initial begin
        rd_clk = 0;
        forever #7 rd_clk = ~rd_clk;
    end

    /*
        复位
    */
    initial begin
        wr_rst_n = 0;
        rd_rst_n = 0;
        wr_en = 0;
        rd_en = 0;
        wr_data = 0;

        #30;
        wr_rst_n = 1;
        rd_rst_n = 1;
    end

    /*
        写数据
    */
    // initial begin
    //     wait(wr_rst_n == 1);

    //     repeat (30) begin
    //         @(posedge wr_clk);
    //         if (!full) begin
    //             wr_en   <= 1;
    //             wr_data <= wr_data + 1;
    //         end else begin
    //             wr_en <= 0;
    //         end
    //     end

    //     @(posedge wr_clk);
    //     wr_en <= 0;
    // end
    integer wr_cnt;

    initial begin
        wait(wr_rst_n == 1);

        wr_cnt = 0;
        while (wr_cnt < 30) begin
            @(posedge wr_clk);
            if (!full) begin
                wr_en   <= 1;
                wr_data <= wr_cnt;
                wr_cnt  <= wr_cnt + 1;
            end else begin
                wr_en <= 0;
            end
        end

        @(posedge wr_clk);
        wr_en <= 0;
    end

    /*
        读数据
    */
    // initial begin
    //     wait(rd_rst_n == 1);

    //     #80;

    //     repeat (30) begin
    //         @(posedge rd_clk);
    //         if (!empty) begin
    //             rd_en <= 1;
    //         end else begin
    //             rd_en <= 0;
    //         end
    //     end

    //     @(posedge rd_clk);
    //     rd_en <= 0;
    // end
    integer rd_cnt;

    initial begin
        wait(rd_rst_n == 1);

        #80;
        rd_cnt = 0;

        while (rd_cnt < 30) begin
            @(posedge rd_clk);
            if (!empty) begin
                rd_en  <= 1;
                rd_cnt <= rd_cnt + 1;
            end else begin
                rd_en <= 0;
            end
        end

        @(posedge rd_clk);
        rd_en <= 0;

        #100;
        $finish;
    end

    /*
        打印读出数据
    */
    // always @(posedge rd_clk) begin
    //     if (rd_en && !empty) begin
    //         $display("[%0t] read data = %0d", $time, rd_data);
    //     end
    // end
    always @(posedge rd_clk) begin
        if (rd_en && !empty) begin
            #1;
            $display("[%0t] read data = %0d", $time, rd_data);
        end
    end

    initial begin
        $dumpfile("wave/tb_async_fifo.vcd");
        $dumpvars(0, tb_async_fifo);

        #1000;
        $finish;
    end



endmodule

verilog/verilog_sim/05_fifo/wave/tb_async_fifo.vcd
$date
	Sun Jun 14 20:34:15 2026
$end
$version
	Icarus Verilog
$end
$timescale
	1ps
$end
$scope module tb_async_fifo $end
$var wire 8 ! rd_data [7:0] $end
$var wire 1 " full $end
$var wire 1 # empty $end
$var reg 1 $ rd_clk $end
$var reg 1 % rd_en $end
$var reg 1 & rd_rst_n $end
$var reg 1 ' wr_clk $end
$var reg 8 ( wr_data [7:0] $end
$var reg 1 ) wr_en $end
$var reg 1 * wr_rst_n $end
$var integer 32 + rd_cnt [31:0] $end
$var integer 32 , wr_cnt [31:0] $end
$scope module u_fifo $end
$var wire 1 $ rd_clk $end
$var wire 1 % rd_en $end
$var wire 9 - rd_gray_next [8:0] $end
$var wire 1 & rd_rst_n $end
$var wire 1 ' wr_clk $end
$var wire 8 . wr_data [7:0] $end
$var wire 1 ) wr_en $end
$var wire 9 / wr_gray_next [8:0] $end
$var wire 1 * wr_rst_n $end
$var wire 9 0 wr_bin_next [8:0] $end
$var wire 9 1 rd_bin_next [8:0] $end
$var wire 1 " full $end
$var wire 1 # empty $end
$var reg 9 2 rd_bin [8:0] $end
$var reg 8 3 rd_data [7:0] $end
$var reg 9 4 rd_gray [8:0] $end
$var reg 9 5 rd_gray_sync1 [8:0] $end
$var reg 9 6 rd_gray_sync2 [8:0] $end
$var reg 9 7 wr_bin [8:0] $end
$var reg 9 8 wr_gray [8:0] $end
$var reg 9 9 wr_gray_sync1 [8:0] $end
$var reg 9 : wr_gray_sync2 [8:0] $end
$upscope $end
$upscope $end
$enddefinitions $end
#0
$dumpvars
b0 :
b0 9
b0 8
b0 7
b0 6
b0 5
b0 4
b0 3
b0 2
b0 1
b0 0
b0 /
b0 .
b0 -
bx ,
bx +
0*
0)
b0 (
0'
0&
0%
0$
1#
0"
b0 !
$end
#5000
1'
#7000
1$
#10000
0'
#14000
0$
#15000
1'
#20000
0'
#21000
1$
#25000
1'
#28000
0$
#30000
b0 ,
0'
1&
1*
#35000
b1 /
b1 0
b1 ,
1)
1'
1$
#40000
0'
#42000
0$
#45000
b11 /
b1 8
b10 0
b1 7
b10 ,
b1 (
b1 .
1'
#49000
b1 9
1$
#50000
0'
#55000
b10 /
b11 8
b11 0
b10 7
b11 ,
b10 (
b10 .
1'
#56000
0$
#60000
0'
#63000
0#
b1 :
b11 9
1$
#65000
b110 /
b10 8
b100 0
b11 7
b100 ,
b11 (
b11 .
1'
#70000
0'
0$
#75000
b111 /
b110 8
b101 0
b100 7
b101 ,
b100 (
b100 .
1'
#77000
b11 :
b110 9
1$
#80000
0'
#84000
0$
#85000
b101 /
b111 8
b110 0
b101 7
b110 ,
b101 (
b101 .
1'
#90000
0'
#91000
b110 :
b111 9
1$
#95000
b100 /
b101 8
b111 0
b110 7
b111 ,
b110 (
b110 .
1'
#98000
0$
#100000
0'
#105000
b1100 /
b100 8
b1000 0
b111 7
b1000 ,
b111 (
b111 .
b111 :
b101 9
1'
1$
#110000
0'
b0 +
#112000
0$
#115000
b1101 /
b1100 8
b1001 0
b1000 7
b1001 ,
b1000 (
b1000 .
1'
#119000
b1 -
b1 1
b101 :
b1100 9
b1 +
1%
1$
#120000
0'
#125000
b1111 /
b1101 8
b1010 0
b1001 7
b1010 ,
b1001 (
b1001 .
1'
#126000
0$
#130000
0'
#133000
b11 -
b1 4
b10 1
b1 2
b1100 :
b1101 9
b10 +
1$
#135000
b1110 /
b1111 8
b1011 0
b1010 7
b1 5
b1011 ,
b1010 (
b1010 .
1'
#140000
0'
0$
#145000
b1010 /
b1 6
b1110 8
b1100 0
b1011 7
b1100 ,
b1011 (
b1011 .
1'
#147000
b10 -
b1101 :
b1110 9
b1 !
b1 3
b11 4
b11 1
b10 2
b11 +
1$
#150000
0'
#154000
0$
#155000
b1011 /
b1010 8
b1101 0
b1100 7
b11 5
b1101 ,
b1100 (
b1100 .
1'
#160000
0'
#161000
b110 -
b10 !
b10 3
b10 4
b100 1
b11 2
b1110 :
b1010 9
b100 +
1$
#165000
b1001 /
b11 6
b10 5
b1011 8
b1110 0
b1101 7
b1110 ,
b1101 (
b1101 .
1'
#168000
0$
#170000
0'
#175000
b1000 /
b111 -
b1001 8
b1111 0
b1110 7
b10 6
b1111 ,
b1110 (
b1110 .
b1010 :
b1011 9
b11 !
b11 3
b110 4
b101 1
b100 2
b101 +
1'
1$
#180000
0'
#182000
0$
#185000
b11000 /
b110 5
b1000 8
b10000 0
b1111 7
b10000 ,
b1111 (
b1111 .
1'
#189000
b101 -
b100 !
b100 3
b111 4
b110 1
b101 2
b1011 :
b1000 9
b110 +
1$
#190000
0'
#195000
b11001 /
b11000 8
b10001 0
b10000 7
b110 6
b111 5
b10001 ,
b10000 (
b10000 .
1'
#196000
0$
#200000
0'
#203000
b100 -
b1000 :
b11000 9
b101 !
b101 3
b101 4
b111 1
b110 2
b111 +
1$
#205000
b11011 /
b111 6
b101 5
b11001 8
b10010 0
b10001 7
b10010 ,
b10001 (
b10001 .
1'
#210000
0'
0$
#215000
b11010 /
b11011 8
b10011 0
b10010 7
b101 6
b10011 ,
b10010 (
b10010 .
1'
#217000
b1100 -
b110 !
b110 3
b100 4
b1000 1
b111 2
b11000 :
b11011 9
b1000 +
1$
#220000
0'
#224000
0$
#225000
b11110 /
b100 5
b11010 8
b10100 0
b10011 7
b10100 ,
b10011 (
b10011 .
1'
#230000
0'
#231000
b1101 -
b11011 :
b11010 9
b111 !
b111 3
b1100 4
b1001 1
b1000 2
b1001 +
1$
#235000
b11111 /
b11110 8
b10101 0
b10100 7
b100 6
b1100 5
b10101 ,
b10100 (
b10100 .
1'
#238000
0$
#240000
0'
#245000
b11101 /
b1111 -
b1100 6
b11111 8
b10110 0
b10101 7
b10110 ,
b10101 (
b10101 .
b1000 !
b1000 3
b1101 4
b1010 1
b1001 2
b11010 :
b11110 9
b1010 +
1'
1$
#250000
0'
#252000
0$
#255000
b11100 /
b11101 8
b10111 0
b10110 7
b1101 5
b10111 ,
b10110 (
b10110 .
1'
#259000
b1110 -
b11110 :
b11101 9
b1001 !
b1001 3
b1111 4
b1011 1
b1010 2
b1011 +
1$
#260000
0'
#265000
b10100 /
b1101 6
b1111 5
b11100 8
b11000 0
b10111 7
b11000 ,
b10111 (
b10111 .
1'
#266000
0$
#270000
0'
#273000
b1010 -
b1010 !
b1010 3
b1110 4
b1100 1
b1011 2
b11101 :
b11100 9
b1100 +
1$
#275000
b10101 /
b10100 8
b11001 0
b11000 7
b1111 6
b1110 5
b11001 ,
b11000 (
b11000 .
1'
#280000
0'
0$
#285000
b10111 /
b1110 6
b10101 8
b11010 0
b11001 7
b11010 ,
b11001 (
b11001 .
1'
#287000
b1011 -
b11100 :
b10101 9
b1011 !
b1011 3
b1010 4
b1101 1
b1100 2
b1101 +
1$
#290000
0'
#294000
0$
#295000
b10110 /
b10111 8
b11011 0
b11010 7
b1010 5
b11011 ,
b11010 (
b11010 .
1'
#300000
0'
#301000
b1001 -
b1100 !
b1100 3
b1011 4
b1110 1
b1101 2
b10101 :
b10111 9
b1110 +
1$
#305000
b10010 /
b1010 6
b1011 5
b10110 8
b11100 0
b11011 7
b11100 ,
b11011 (
b11011 .
1'
#308000
0$
#310000
0'
#315000
b10011 /
b1000 -
b10010 8
b11101 0
b11100 7
b1011 6
b11101 ,
b11100 (
b11100 .
b10111 :
b10110 9
b1101 !
b1101 3
b1001 4
b1111 1
b1110 2
b1111 +
1'
1$
#320000
0'
#322000
0$
#325000
b10001 /
b1001 5
b10011 8
b11110 0
b11101 7
b11110 ,
b11101 (
b11101 .
1'
#329000
b11000 -
b1110 !
b1110 3
b1000 4
b10000 1
b1111 2
b10110 :
b10011 9
b10000 +
1$
#330000
0'
#335000
b10000 /
b10001 8
b11111 0
b11110 7
b1001 6
b1000 5
b11111 ,
b11110 (
b11110 .
1'
#336000
0$
#340000
0'
#343000
b11001 -
b10011 :
b10001 9
b1111 !
b1111 3
b11000 4
b10001 1
b10000 2
b10001 +
1$
#345000
b10000 /
b1000 6
b11000 5
b10000 8
b11111 0
b11111 7
0)
1'
#350000
0'
0$
#355000
b11000 6
1'
#357000
b11011 -
b10000 !
b10000 3
b11001 4
b10010 1
b10001 2
b10001 :
b10000 9
b10010 +
1$
#360000
0'
#364000
0$
#365000
b11001 5
1'
#370000
0'
#371000
b11010 -
b10000 :
b10001 !
b10001 3
b11011 4
b10011 1
b10010 2
b10011 +
1$
#375000
b11001 6
b11011 5
1'
#378000
0$
#380000
0'
#385000
b11110 -
b11011 6
b10010 !
b10010 3
b11010 4
b10100 1
b10011 2
b10100 +
1'
1$
#390000
0'
#392000
0$
#395000
b11010 5
1'
#399000
b11111 -
b10011 !
b10011 3
b11110 4
b10101 1
b10100 2
b10101 +
1$
#400000
0'
#405000
b11010 6
b11110 5
1'
#406000
0$
#410000
0'
#413000
b11101 -
b10100 !
b10100 3
b11111 4
b10110 1
b10101 2
b10110 +
1$
#415000
b11110 6
b11111 5
1'
#420000
0'
0$
#425000
b11111 6
1'
#427000
b11100 -
b10101 !
b10101 3
b11101 4
b10111 1
b10110 2
b10111 +
1$
#430000
0'
#434000
0$
#435000
b11101 5
1'
#440000
0'
#441000
b10100 -
b10110 !
b10110 3
b11100 4
b11000 1
b10111 2
b11000 +
1$
#445000
b11101 6
b11100 5
1'
#448000
0$
#450000
0'
#455000
b10101 -
b11100 6
b10111 !
b10111 3
b10100 4
b11001 1
b11000 2
b11001 +
1'
1$
#460000
0'
#462000
0$
#465000
b10100 5
1'
#469000
b10111 -
b11000 !
b11000 3
b10101 4
b11010 1
b11001 2
b11010 +
1$
#470000
0'
#475000
b10100 6
b10101 5
1'
#476000
0$
#480000
0'
#483000
b10110 -
b11001 !
b11001 3
b10111 4
b11011 1
b11010 2
b11011 +
1$
#485000
b10101 6
b10111 5
1'
#490000
0'
0$
#495000
b10111 6
1'
#497000
b10010 -
b11010 !
b11010 3
b10110 4
b11100 1
b11011 2
b11100 +
1$
#500000
0'
#504000
0$
#505000
b10110 5
1'
#510000
0'
#511000
b10011 -
b11011 !
b11011 3
b10010 4
b11101 1
b11100 2
b11101 +
1$
#515000
b10110 6
b10010 5
1'
