verilog/verilog_sim/02_syntax_test/src/adder4b_half.v
`timescale 1 ns/1 ns  

module adder4b_half(  
    input clk     ,  
    input rst_n   ,


    input       [3 : 0]  a  ,  
    input       [3 : 0]  b  ,
    output reg  [4 : 0]  out 
);

    always@(posedge clk or negedge rst_n) begin 
        if(rst_n==1'b0)
            out <= 4'd0;  
        else 
            out <= a + b;  
    end


endmodule

verilog/verilog_sim/02_syntax_test/tb/tb_delay.v
`timescale 1 ns/1 ns  

module tb_delay();  
    reg                        clk   ;//系统时钟，默认100MHz；  
    reg                        rst_n ;//系统复位，默认低电平有效；  
    reg         [3 : 0]        a;  
    reg         [3 : 0]        b;
    wire        [4 : 0]        out  ;  
    
    adder4b_half  dut_adder4b_half (  
        .clk   ( clk       ),  
        .rst_n ( rst_n     ),  
        .a     ( a         ),  
        .b     ( b         ),  
        .out   ( out       )  
    );  

    initial begin  
        clk = 1;  
        forever #5 clk=~clk;  
    end
    // always #5 clk = ~clk;

    initial begin  
        rst_n = 0;//开始时复位10个时钟；  
        #50;  
        rst_n = 1;  
    end  

    initial begin
        $dumpfile("wave/tb_delay.vcd");
        $dumpvars(0, tb_delay);
    end

    initial begin  
        a = 0; 
        b = 0; 
        
        // 使用 #10 延时 
        #100;
        repeat(10) begin
            #10;  
            a = {$random} % 16;  
            b = {$random} % 16;  
        end
        // 表现出组合逻辑的效果：输出与输入是对齐的
        // 原因是输入值改变发生在时钟上升沿，触发器在上升沿采样到了新值，立即更新输出  

        // 使用 #10 延时，且整体延时 1ns
        #10;
        a = 0; 
        b = 0; 
        #50;
        #1;
        repeat(10) begin
            #10;  
            a = {$random} % 16;  
            b = {$random} % 16;  
        end
        // 表现出时序逻辑的效果：输出比输入落后一个周期
        // 这样其实类似于在下降沿改变数据，保证了充足的

        // 使用 @(posedge clk)，放在 repeat 后
        #9;
        a = 0; 
        b = 0; 
        #50;
        repeat(10) @(posedge clk) begin
            a = {$random} % 16;  
            b = {$random} % 16;  
        end 
        // 表现出组合逻辑的效果：输出与输入是对齐的

        // 使用 @(posedge clk)，放在循环体内
        #10;
        a = 0; 
        b = 0; 
        #50;
        repeat(10) begin
            @(posedge clk);
            a = {$random} % 16;  
            b = {$random} % 16;  
        end 
        // 表现出组合逻辑的效果：输出与输入是对齐的

        // 使用 @(posedge clk)，放在循环体内
        // 使用非阻塞赋值
        #10;
        a = 0; 
        b = 0; 
        #50;
        repeat(10) begin
            @(posedge clk);
            a <= {$random} % 16;  
            b <= {$random} % 16;  
        end 
        // 表现出时序逻辑的效果：输出比输入落后一个周期
        

        #50;
        $finish;//停止仿真；  
    end


endmodule

verilog/verilog_sim/02_syntax_test/wave/tb_delay.vcd
$date
	Mon Jun 15 15:47:10 2026
$end
$version
	Icarus Verilog
$end
$timescale
	1ns
$end
$scope module tb_delay $end
$var wire 5 ! out [4:0] $end
$var reg 4 " a [3:0] $end
$var reg 4 # b [3:0] $end
$var reg 1 $ clk $end
$var reg 1 % rst_n $end
$scope module dut_adder4b_half $end
$var wire 4 & a [3:0] $end
$var wire 4 ' b [3:0] $end
$var wire 1 $ clk $end
$var wire 1 % rst_n $end
$var reg 5 ( out [4:0] $end
$upscope $end
$upscope $end
$enddefinitions $end
#0
$dumpvars
b0 (
b0 '
b0 &
0%
1$
b0 #
b0 "
b0 !
$end
#5
0$
#10
1$
#15
0$
#20
1$
#25
0$
#30
1$
#35
0$
#40
1$
#45
0$
#50
1$
1%
#55
0$
#60
1$
#65
0$
#70
1$
#75
0$
#80
1$
#85
0$
#90
1$
#95
0$
#100
1$
#105
0$
#110
b101 !
b101 (
1$
b1 #
b1 '
b100 "
b100 &
#115
0$
#120
b1100 !
b1100 (
1$
b11 #
b11 '
b1001 "
b1001 &
#125
0$
#130
b11010 !
b11010 (
1$
b1101 #
b1101 '
b1101 "
b1101 &
#135
0$
#140
b111 !
b111 (
1$
b10 #
b10 '
b101 "
b101 &
#145
0$
#150
b1110 !
b1110 (
1$
b1101 #
b1101 '
b1 "
b1 &
#155
0$
#160
b10011 !
b10011 (
1$
b110 "
b110 &
#165
0$
#170
b11001 !
b11001 (
1$
b1100 #
b1100 '
b1101 "
b1101 &
#175
0$
#180
b1111 !
b1111 (
1$
b110 #
b110 '
b1001 "
b1001 &
#185
0$
#190
1$
b1010 #
b1010 '
b101 "
b101 &
#195
0$
#200
b1100 !
b1100 (
1$
b111 #
b111 '
#205
0$
#210
b0 !
b0 (
1$
b0 #
b0 '
b0 "
b0 &
#215
0$
#220
1$
#225
0$
#230
1$
#235
0$
#240
1$
#245
0$
#250
1$
#255
0$
#260
1$
#265
0$
#270
1$
#271
b1111 #
b1111 '
b10 "
b10 &
#275
0$
#280
b10001 !
b10001 (
1$
#281
b1110 #
b1110 '
#285
0$
#290
b10000 !
b10000 (
1$
#291
b101 #
b101 '
b1000 "
b1000 &
#295
0$
#300
b1101 !
b1101 (
1$
#301
b1101 #
b1101 '
b1100 "
b1100 &
#305
0$
#310
b11001 !
b11001 (
1$
#311
b101 #
b101 '
b1101 "
b1101 &
#315
0$
#320
b10010 !
b10010 (
1$
#321
b1010 #
b1010 '
b11 "
b11 &
#325
0$
#330
b1101 !
b1101 (
1$
#331
b0 #
b0 '
b0 "
b0 &
#335
0$
#340
b0 !
b0 (
1$
#341
b1101 #
b1101 '
b1010 "
b1010 &
#345
0$
#350
b10111 !
b10111 (
1$
#351
b11 #
b11 '
b110 "
b110 &
#355
0$
#360
b1001 !
b1001 (
1$
#361
b1101 "
b1101 &
#365
0$
#370
b0 !
b0 (
1$
b0 #
b0 '
b0 "
b0 &
#375
0$
#380
1$
#385
0$
#390
1$
#395
0$
#400
1$
#405
0$
#410
1$
#415
0$
#420
b10000 !
b10000 (
b101 #
b101 '
b1011 "
b1011 &
1$
#425
0$
#430
b1110 #
b1110 '
b10 "
b10 &
1$
#435
0$
#440
b11100 !
b11100 (
b1111 #
b1111 '
b1101 "
b1101 &
1$
#445
0$
#450
b1101 !
b1101 (
b1010 #
b1010 '
b11 "
b11 &
1$
#455
0$
#460
b10110 !
b10110 (
b1100 #
b1100 '
b1010 "
b1010 &
1$
#465
0$
#470
b1100 !
b1100 (
b1010 #
b1010 '
b10 "
b10 &
1$
#475
0$
#480
b1001 !
b1001 (
b1000 #
b1000 '
b1 "
b1 &
1$
#485
0$
#490
b10001 !
b10001 (
b1001 #
b1001 '
b1000 "
b1000 &
1$
#495
0$
#500
b110 #
b110 '
b1011 "
b1011 &
1$
#505
0$
#510
b10100 !
b10100 (
b1110 #
b1110 '
b110 "
b110 &
1$
#515
0$
#520
b0 !
b0 (
1$
b0 #
b0 '
b0 "
b0 &
#525
0$
#530
1$
#535
0$
#540
1$
#545
0$
#550
1$
#555
0$
#560
1$
#565
0$
#570
b10110 !
b10110 (
b1010 #
b1010 '
b1100 "
b1100 &
1$
#575
0$
#580
b1100 !
b1100 (
b1 #
b1 '
b1011 "
b1011 &
1$
#585
0$
#590
b10100 !
b10100 (
b1111 #
b1111 '
b101 "
b101 &
1$
#595
0$
#600
b10101 !
b10101 (
b1010 #
b1010 '
b1011 "
b1011 &
1$
#605
0$
#610
b10011 !
b10011 (
b101 #
b101 '
b1110 "
b1110 &
1$
#615
0$
#620
b1010 !
b1010 (
b1001 #
b1001 '
b1 "
b1 &
1$
#625
0$
#630
b1110 !
b1110 (
b1100 #
b1100 '
b10 "
b10 &
1$
#635
0$
#640
b11110 !
b11110 (
b1111 #
b1111 '
b1111 "
b1111 &
1$
#645
0$
#650
b1111 !
b1111 (
b111 #
b111 '
b1000 "
b1000 &
1$
#655
0$
#660
b11011 !
b11011 (
b1100 #
b1100 '
b1111 "
b1111 &
1$
#665
0$
#670
b0 !
b0 (
1$
b0 #
b0 '
b0 "
b0 &
#675
0$
#680
1$
#685
0$
#690
1$
#695
0$
#700
1$
#705
0$
#710
1$
#715
0$
#720
b1001 #
b1001 '
b1011 "
b1011 &
1$
#725
0$
#730
b10100 !
b10100 (
b0 #
b0 '
b1001 "
b1001 &
1$
#735
0$
#740
b1001 !
b1001 (
b1 #
b1 '
b111 "
b111 &
1$
#745
0$
#750
b1000 !
b1000 (
b1100 #
b1100 '
b110 "
b110 &
1$
#755
0$
#760
b10010 !
b10010 (
b1000 #
b1000 '
b10 "
b10 &
1$
#765
0$
#770
b1010 !
b1010 (
b1101 #
b1101 '
b111 "
b111 &
1$
#775
0$
#780
b10100 !
b10100 (
b1110 #
b1110 '
b10 "
b10 &
1$
#785
0$
#790
b10000 !
b10000 (
b1001 #
b1001 '
b1101 "
b1101 &
1$
#795
0$
#800
b10110 !
b10110 (
b11 #
b11 '
b1111 "
b1111 &
1$
#805
0$
#810
b10010 !
b10010 (
b1000 #
b1000 '
b101 "
b101 &
1$
#815
0$
#820
b1101 !
b1101 (
1$
