verilog/verilog_sim/06_riscv/src/rv32_defs.vh
`ifndef RV32_DEFS_VH
`define RV32_DEFS_VH

`define RV32_ALU_ADD   4'd0
`define RV32_ALU_SUB   4'd1
`define RV32_ALU_SLL   4'd2   // 逻辑左移
`define RV32_ALU_SLT   4'd3   // 有符号数小于比较，若 a<b 则输出1
`define RV32_ALU_SLTU  4'd4   // 无符号数小于比较，若 a<b 则输出1
`define RV32_ALU_XOR   4'd5
`define RV32_ALU_SRL   4'd6   // 逻辑右移
`define RV32_ALU_SRA   4'd7   // 算术右移
`define RV32_ALU_OR    4'd8
`define RV32_ALU_AND   4'd9

`define RV32_IMM_I     3'd0
`define RV32_IMM_S     3'd1
`define RV32_IMM_B     3'd2
`define RV32_IMM_U     3'd3
`define RV32_IMM_J     3'd4

`define RV32_WB_ALU    2'd0
`define RV32_WB_MEM    2'd1
`define RV32_WB_PC4    2'd2

`define RV32_OP_LOAD    7'b0000011
`define RV32_OP_MISC    7'b0001111
`define RV32_OP_OPIMM   7'b0010011
`define RV32_OP_AUIPC   7'b0010111
`define RV32_OP_STORE   7'b0100011
`define RV32_OP_OP      7'b0110011
`define RV32_OP_LUI     7'b0110111
`define RV32_OP_BRANCH  7'b1100011
`define RV32_OP_JALR    7'b1100111
`define RV32_OP_JAL     7'b1101111
`define RV32_OP_SYSTEM  7'b1110011

`endif

verilog/verilog_sim/06_riscv/src/rv32_alu.v
`include "rv32_defs.vh"

module rv32_alu (
    input  wire [31:0] a,
    input  wire [31:0] b,
    input  wire [3:0]  op,
    output reg  [31:0] y
);
    always @* begin
        case (op)
            `RV32_ALU_ADD:  y = a + b;
            `RV32_ALU_SUB:  y = a - b;
            `RV32_ALU_SLL:  y = a << b[4:0];  
            `RV32_ALU_SLT:  y = ($signed(a) < $signed(b)) ? 32'd1 : 32'd0;
            `RV32_ALU_SLTU: y = (a < b) ? 32'd1 : 32'd0;
            `RV32_ALU_XOR:  y = a ^ b;
            `RV32_ALU_SRL:  y = a >> b[4:0];
            `RV32_ALU_SRA:  y = $signed(a) >>> b[4:0];
            `RV32_ALU_OR:   y = a | b;
            `RV32_ALU_AND:  y = a & b;
            default:        y = 32'b0;
        endcase
    end
endmodule

verilog/verilog_sim/06_riscv/tb/tb_alu.v
`timescale 1ns/1ps
`include "rv32_defs.vh"

module tb_alu;
    reg  [31:0] a;
    reg  [31:0] b;
    reg  [3:0]  op;
    wire [31:0] y;
    integer errors;

    initial begin
        //! 这里的当前目录是 makefile 所在目录，所以不需要加 ../
        $dumpfile("wave/tb_alu.vcd");
        $dumpvars(0, tb_alu);
    end

    rv32_alu dut (  .a(a), 
                    .b(b), 
                    .op(op), 
                    .y(y));

    task check;
        input [3:0]  t_op;
        input [31:0] t_a;
        input [31:0] t_b;
        input [31:0] expected;
        begin
            op = t_op; a = t_a; b = t_b; #1;
            if (y !== expected) begin
                $display("ALU FAIL op=%0d a=%h b=%h got=%h expected=%h",
                         t_op, t_a, t_b, y, expected);
                errors = errors + 1;
            end
        end
    endtask

    initial begin
        errors = 0;
        check(`RV32_ALU_ADD,  32'd7, 32'd5, 32'd12);
        check(`RV32_ALU_SUB,  32'd7, 32'd5, 32'd2);
        check(`RV32_ALU_SLL,  32'h1, 32'd31, 32'h8000_0000);
        check(`RV32_ALU_SLT,  32'hffff_ffff, 32'd1, 32'd1);
        check(`RV32_ALU_SLTU, 32'hffff_ffff, 32'd1, 32'd0);
        check(`RV32_ALU_XOR,  32'h55aa_00ff, 32'hffff_0000, 32'haa55_00ff);
        check(`RV32_ALU_SRL,  32'h8000_0000, 32'd4, 32'h0800_0000);
        check(`RV32_ALU_SRA,  32'h8000_0000, 32'd4, 32'hf800_0000);
        check(`RV32_ALU_OR,   32'h5500_00ff, 32'h00aa_ff00, 32'h55aa_ffff);
        check(`RV32_ALU_AND,  32'h55aa_00ff, 32'h0ff0_0ff0, 32'h05a0_00f0);
        if (errors == 0) $display("TB_ALU PASS");
        else $fatal(1, "TB_ALU FAIL: %0d errors", errors);
        $finish;
    end
endmodule

verilog/verilog_sim/06_riscv/wave/tb_alu.vcd
$date
	Wed Aug 26 11:55:24 2026
$end
$version
	Icarus Verilog
$end
$timescale
	1ps
$end
$scope module tb_alu $end
$var wire 32 ! y [31:0] $end
$var reg 32 " a [31:0] $end
$var reg 32 # b [31:0] $end
$var reg 4 $ op [3:0] $end
$var integer 32 % errors [31:0] $end
$scope module dut $end
$var wire 32 & a [31:0] $end
$var wire 32 ' b [31:0] $end
$var wire 4 ( op [3:0] $end
$var reg 32 ) y [31:0] $end
$upscope $end
$scope task check $end
$var reg 32 * expected [31:0] $end
$var reg 32 + t_a [31:0] $end
$var reg 32 , t_b [31:0] $end
$var reg 4 - t_op [3:0] $end
$upscope $end
$upscope $end
$enddefinitions $end
#0
$dumpvars
b0 -
b101 ,
b111 +
b1100 *
b1100 )
b0 (
b101 '
b111 &
b0 %
b0 $
b101 #
b111 "
b1100 !
$end
#1000
b10 !
b10 )
b1 $
b1 (
b10 *
b1 -
#2000
b10000000000000000000000000000000 !
b10000000000000000000000000000000 )
b11111 #
b11111 '
b1 "
b1 &
b10 $
b10 (
b10000000000000000000000000000000 *
b11111 ,
b1 +
b10 -
#3000
b1 !
b1 )
b1 #
b1 '
b11111111111111111111111111111111 "
b11111111111111111111111111111111 &
b11 $
b11 (
b1 *
b1 ,
b11111111111111111111111111111111 +
b11 -
#4000
b0 !
b0 )
b100 $
b100 (
b0 *
b100 -
#5000
b10101010010101010000000011111111 !
b10101010010101010000000011111111 )
b11111111111111110000000000000000 #
b11111111111111110000000000000000 '
b1010101101010100000000011111111 "
b1010101101010100000000011111111 &
b101 $
b101 (
b10101010010101010000000011111111 *
b11111111111111110000000000000000 ,
b1010101101010100000000011111111 +
b101 -
#6000
b1000000000000000000000000000 !
b1000000000000000000000000000 )
b100 #
b100 '
b10000000000000000000000000000000 "
b10000000000000000000000000000000 &
b110 $
b110 (
b1000000000000000000000000000 *
b100 ,
b10000000000000000000000000000000 +
b110 -
#7000
b11111000000000000000000000000000 !
b11111000000000000000000000000000 )
b111 $
b111 (
b11111000000000000000000000000000 *
b111 -
#8000
b1010101101010101111111111111111 !
b1010101101010101111111111111111 )
b101010101111111100000000 #
b101010101111111100000000 '
b1010101000000000000000011111111 "
b1010101000000000000000011111111 &
b1000 $
b1000 (
b1010101101010101111111111111111 *
b101010101111111100000000 ,
b1010101000000000000000011111111 +
b1000 -
#9000
b101101000000000000011110000 !
b101101000000000000011110000 )
b1111111100000000111111110000 #
b1111111100000000111111110000 '
b1010101101010100000000011111111 "
b1010101101010100000000011111111 &
b1001 $
b1001 (
b101101000000000000011110000 *
b1111111100000000111111110000 ,
b1010101101010100000000011111111 +
b1001 -
