verilog/verilog_sim/06_riscv/src/rv32_defs.vh
`ifndef RV32_DEFS_VH
`define RV32_DEFS_VH

`define RV32_ALU_ADD   4'd0
`define RV32_ALU_SUB   4'd1
`define RV32_ALU_SLL   4'd2   // 逻辑左移
`define RV32_ALU_SLT   4'd3   // 有符号数小于比较，若 a<b 则输出1
`define RV32_ALU_SLTU  4'd4   // 无符号数小于比较，若 a<b 则输出1
`define RV32_ALU_XOR   4'd5
`define RV32_ALU_SRL   4'd6   // 逻辑右移
`define RV32_ALU_SRA   4'd7   // 算术右移
`define RV32_ALU_OR    4'd8
`define RV32_ALU_AND   4'd9

`define RV32_IMM_I     3'd0
`define RV32_IMM_S     3'd1
`define RV32_IMM_B     3'd2
`define RV32_IMM_U     3'd3
`define RV32_IMM_J     3'd4

`define RV32_WB_ALU    2'd0
`define RV32_WB_MEM    2'd1
`define RV32_WB_PC4    2'd2

`define RV32_OP_LOAD    7'b0000011
`define RV32_OP_MISC    7'b0001111
`define RV32_OP_OPIMM   7'b0010011
`define RV32_OP_AUIPC   7'b0010111
`define RV32_OP_STORE   7'b0100011
`define RV32_OP_OP      7'b0110011
`define RV32_OP_LUI     7'b0110111
`define RV32_OP_BRANCH  7'b1100011
`define RV32_OP_JALR    7'b1100111
`define RV32_OP_JAL     7'b1101111
`define RV32_OP_SYSTEM  7'b1110011

`endif

verilog/verilog_sim/06_riscv/src/rv32_regfile.v
module rv32_regfile (
    input  wire        clk,
    input  wire        rst_n,
    input  wire [4:0]  rs1_addr,
    input  wire [4:0]  rs2_addr,
    output wire [31:0] rs1_data,
    output wire [31:0] rs2_data,
    input  wire        rd_we,
    input  wire [4:0]  rd_addr,
    input  wire [31:0] rd_data
);
    reg [31:0] regs [0:31];
    integer i;

    assign rs1_data = (rs1_addr == 5'd0) ? 32'b0 : regs[rs1_addr];
    assign rs2_data = (rs2_addr == 5'd0) ? 32'b0 : regs[rs2_addr];

    always @(posedge clk or negedge rst_n) begin
        if (!rst_n) begin
            for (i = 0; i < 32; i = i + 1)
                regs[i] <= 32'b0;
        end else if (rd_we && (rd_addr != 5'd0)) begin
            regs[rd_addr] <= rd_data;
        end
    end
endmodule

verilog/verilog_sim/06_riscv/src/rv32_alu.v
`include "rv32_defs.vh"

module rv32_alu (
    input  wire [31:0] a,
    input  wire [31:0] b,
    input  wire [3:0]  op,
    output reg  [31:0] y
);
    always @* begin
        case (op)
            `RV32_ALU_ADD:  y = a + b;
            `RV32_ALU_SUB:  y = a - b;
            `RV32_ALU_SLL:  y = a << b[4:0];  
            `RV32_ALU_SLT:  y = ($signed(a) < $signed(b)) ? 32'd1 : 32'd0;
            `RV32_ALU_SLTU: y = (a < b) ? 32'd1 : 32'd0;
            `RV32_ALU_XOR:  y = a ^ b;
            `RV32_ALU_SRL:  y = a >> b[4:0];
            `RV32_ALU_SRA:  y = $signed(a) >>> b[4:0];
            `RV32_ALU_OR:   y = a | b;
            `RV32_ALU_AND:  y = a & b;
            default:        y = 32'b0;
        endcase
    end
endmodule

verilog/verilog_sim/06_riscv/src/rv32_immgen.v
`include "rv32_defs.vh"

module rv32_immgen (
    input  wire [31:0] instr,
    input  wire [2:0]  imm_sel,
    output reg  [31:0] imm
);
    always @* begin
        case (imm_sel)
            `RV32_IMM_I: imm = {{20{instr[31]}}, instr[31:20]};
            `RV32_IMM_S: imm = {{20{instr[31]}}, instr[31:25], instr[11:7]};
            `RV32_IMM_B: imm = {{19{instr[31]}}, instr[31], instr[7],
                                instr[30:25], instr[11:8], 1'b0};
            `RV32_IMM_U: imm = {instr[31:12], 12'b0};
            `RV32_IMM_J: imm = {{11{instr[31]}}, instr[31], instr[19:12],
                                instr[20], instr[30:21], 1'b0};
            default:     imm = 32'b0;
        endcase
    end
endmodule

verilog/verilog_sim/06_riscv/src/rv32_decoder.v
`include "rv32_defs.vh"

module rv32_decoder (
    input  wire [31:0] instr,
    output reg         reg_write,
    output reg         alu_src_pc,
    output reg         alu_src_imm,
    output reg  [3:0]  alu_op,
    output reg  [1:0]  wb_sel,
    output reg         mem_read,
    output reg         mem_write,
    output reg         branch,
    output reg         jump,
    output reg         jalr,
    output reg  [2:0]  imm_sel,
    output reg         illegal
);
    wire [6:0] opcode = instr[6:0];
    wire [2:0] funct3 = instr[14:12];
    wire [6:0] funct7 = instr[31:25];

    always @* begin
        reg_write  = 1'b0;
        alu_src_pc = 1'b0;
        alu_src_imm= 1'b0;
        alu_op     = `RV32_ALU_ADD;
        wb_sel     = `RV32_WB_ALU;
        mem_read   = 1'b0;
        mem_write  = 1'b0;
        branch     = 1'b0;
        jump       = 1'b0;
        jalr       = 1'b0;
        imm_sel    = `RV32_IMM_I;
        illegal    = 1'b0;

        case (opcode)
            `RV32_OP_LUI: begin
                reg_write   = 1'b1;
                alu_src_imm = 1'b1;
                imm_sel     = `RV32_IMM_U;
            end
            `RV32_OP_AUIPC: begin
                reg_write   = 1'b1;
                alu_src_pc  = 1'b1;
                alu_src_imm = 1'b1;
                imm_sel     = `RV32_IMM_U;
            end
            `RV32_OP_JAL: begin
                reg_write = 1'b1;
                wb_sel    = `RV32_WB_PC4;
                jump      = 1'b1;
                imm_sel   = `RV32_IMM_J;
            end
            `RV32_OP_JALR: begin
                reg_write = 1'b1;
                wb_sel    = `RV32_WB_PC4;
                jump      = 1'b1;
                jalr      = 1'b1;
                imm_sel   = `RV32_IMM_I;
                if (funct3 != 3'b000)
                    illegal = 1'b1;
            end
            `RV32_OP_BRANCH: begin
                branch   = 1'b1;
                imm_sel  = `RV32_IMM_B;
                if (!((funct3 == 3'b000) || (funct3 == 3'b001) ||
                      (funct3 == 3'b100) || (funct3 == 3'b101) ||
                      (funct3 == 3'b110) || (funct3 == 3'b111)))
                    illegal = 1'b1;
            end
            `RV32_OP_LOAD: begin
                reg_write   = 1'b1;
                alu_src_imm = 1'b1;
                wb_sel      = `RV32_WB_MEM;
                mem_read    = 1'b1;
                imm_sel     = `RV32_IMM_I;
                if (!((funct3 == 3'b000) || (funct3 == 3'b001) ||
                      (funct3 == 3'b010) || (funct3 == 3'b100) ||
                      (funct3 == 3'b101)))
                    illegal = 1'b1;
            end
            `RV32_OP_STORE: begin
                alu_src_imm = 1'b1;
                mem_write   = 1'b1;
                imm_sel     = `RV32_IMM_S;
                if (!((funct3 == 3'b000) || (funct3 == 3'b001) ||
                      (funct3 == 3'b010)))
                    illegal = 1'b1;
            end
            `RV32_OP_OPIMM: begin
                reg_write   = 1'b1;
                alu_src_imm = 1'b1;
                imm_sel     = `RV32_IMM_I;
                case (funct3)
                    3'b000: alu_op = `RV32_ALU_ADD;
                    3'b010: alu_op = `RV32_ALU_SLT;
                    3'b011: alu_op = `RV32_ALU_SLTU;
                    3'b100: alu_op = `RV32_ALU_XOR;
                    3'b110: alu_op = `RV32_ALU_OR;
                    3'b111: alu_op = `RV32_ALU_AND;
                    3'b001: begin
                        alu_op = `RV32_ALU_SLL;
                        if (funct7 != 7'b0000000) illegal = 1'b1;
                    end
                    3'b101: begin
                        if (funct7 == 7'b0000000)
                            alu_op = `RV32_ALU_SRL;
                        else if (funct7 == 7'b0100000)
                            alu_op = `RV32_ALU_SRA;
                        else
                            illegal = 1'b1;
                    end
                    default: illegal = 1'b1;
                endcase
            end
            `RV32_OP_OP: begin
                reg_write = 1'b1;
                case (funct3)
                    3'b000: begin
                        if (funct7 == 7'b0000000) alu_op = `RV32_ALU_ADD;
                        else if (funct7 == 7'b0100000) alu_op = `RV32_ALU_SUB;
                        else illegal = 1'b1;
                    end
                    3'b001: begin alu_op = `RV32_ALU_SLL;  if (funct7 != 0) illegal = 1'b1; end
                    3'b010: begin alu_op = `RV32_ALU_SLT;  if (funct7 != 0) illegal = 1'b1; end
                    3'b011: begin alu_op = `RV32_ALU_SLTU; if (funct7 != 0) illegal = 1'b1; end
                    3'b100: begin alu_op = `RV32_ALU_XOR;  if (funct7 != 0) illegal = 1'b1; end
                    3'b101: begin
                        if (funct7 == 7'b0000000) alu_op = `RV32_ALU_SRL;
                        else if (funct7 == 7'b0100000) alu_op = `RV32_ALU_SRA;
                        else illegal = 1'b1;
                    end
                    3'b110: begin alu_op = `RV32_ALU_OR;   if (funct7 != 0) illegal = 1'b1; end
                    3'b111: begin alu_op = `RV32_ALU_AND;  if (funct7 != 0) illegal = 1'b1; end
                    default: illegal = 1'b1;
                endcase
            end
            `RV32_OP_MISC: begin
                if (!((funct3 == 3'b000) || (funct3 == 3'b001)))
                    illegal = 1'b1;
            end
            `RV32_OP_SYSTEM: begin
                // ECALL/EBREAK/CSR are added in the privileged-architecture stage.
                illegal = 1'b1;
            end
            default: illegal = 1'b1;
        endcase
    end
endmodule

verilog/verilog_sim/06_riscv/src/rv32_core_singlecycle.v
`include "rv32_defs.vh"

module rv32_core_singlecycle #(
    parameter RESET_PC = 32'h0000_0000
) (
    input  wire        clk,
    input  wire        rst_n,

    output wire [31:0] imem_addr,
    input  wire [31:0] imem_rdata,

    output wire        dmem_valid,
    output wire        dmem_we,
    output reg  [3:0]  dmem_wstrb,
    output wire [31:0] dmem_addr,
    output reg  [31:0] dmem_wdata,
    input  wire [31:0] dmem_rdata,

    output reg         trap,
    output reg  [31:0] trap_pc,
    output wire [31:0] dbg_pc,
    output wire [31:0] dbg_instr
);
    reg [31:0] pc;

    wire [4:0] rs1_addr = imem_rdata[19:15];
    wire [4:0] rs2_addr = imem_rdata[24:20];
    wire [4:0] rd_addr  = imem_rdata[11:7];
    wire [2:0] funct3   = imem_rdata[14:12];

    wire        reg_write_dec;
    wire        alu_src_pc;
    wire        alu_src_imm;
    wire [3:0]  alu_op;
    wire [1:0]  wb_sel;
    wire        mem_read;
    wire        mem_write;
    wire        branch;
    wire        jump;
    wire        jalr;
    wire [2:0]  imm_sel;
    wire        illegal_dec;
    wire [31:0] imm;
    wire [31:0] rs1_data;
    wire [31:0] rs2_data;
    wire        is_lui = (imem_rdata[6:0] == `RV32_OP_LUI);
    wire [31:0] alu_a = is_lui ? 32'b0 : (alu_src_pc ? pc : rs1_data);
    wire [31:0] alu_b = alu_src_imm ? imm : rs2_data;
    wire [31:0] alu_y;

    reg         branch_taken;
    reg  [31:0] load_data;
    wire [31:0] shifted_rdata = dmem_rdata >> ({dmem_addr[1:0], 3'b000});
    wire [31:0] pc_plus4 = pc + 32'd4;
    wire [31:0] direct_target = pc + imm;
    wire [31:0] jump_target = jalr ? ((rs1_data + imm) & 32'hffff_fffe)
                                         : direct_target;
    wire [31:0] control_target = jump ? jump_target : direct_target;
    wire        control_taken = jump | (branch & branch_taken);
    wire        instr_misaligned = control_taken && (control_target[1:0] != 2'b00);

    reg mem_misaligned;
    wire fault_now = illegal_dec | mem_misaligned | instr_misaligned;

    reg [31:0] wb_data;
    wire rd_we = reg_write_dec && !fault_now && !trap;

    assign imem_addr = pc;
    assign dmem_addr = alu_y;
    assign dmem_valid = (mem_read | mem_write) && !fault_now && !trap;
    assign dmem_we = mem_write;
    assign dbg_pc = pc;
    assign dbg_instr = imem_rdata;

    rv32_decoder u_decoder (
        .instr(imem_rdata), .reg_write(reg_write_dec),
        .alu_src_pc(alu_src_pc), .alu_src_imm(alu_src_imm), .alu_op(alu_op),
        .wb_sel(wb_sel), .mem_read(mem_read), .mem_write(mem_write),
        .branch(branch), .jump(jump), .jalr(jalr), .imm_sel(imm_sel),
        .illegal(illegal_dec)
    );

    rv32_immgen u_immgen (.instr(imem_rdata), .imm_sel(imm_sel), .imm(imm));
    rv32_alu u_alu (.a(alu_a), .b(alu_b), .op(alu_op), .y(alu_y));
    rv32_regfile u_regfile (
        .clk(clk), .rst_n(rst_n), .rs1_addr(rs1_addr), .rs2_addr(rs2_addr),
        .rs1_data(rs1_data), .rs2_data(rs2_data), .rd_we(rd_we),
        .rd_addr(rd_addr), .rd_data(wb_data)
    );

    always @* begin
        case (funct3)
            3'b000: branch_taken = (rs1_data == rs2_data);                    // BEQ
            3'b001: branch_taken = (rs1_data != rs2_data);                    // BNE
            3'b100: branch_taken = ($signed(rs1_data) < $signed(rs2_data));   // BLT
            3'b101: branch_taken = ($signed(rs1_data) >= $signed(rs2_data));  // BGE
            3'b110: branch_taken = (rs1_data < rs2_data);                     // BLTU
            3'b111: branch_taken = (rs1_data >= rs2_data);                    // BGEU
            default: branch_taken = 1'b0;
        endcase
    end

    always @* begin
        load_data = 32'b0;
        case (funct3)
            3'b000: load_data = {{24{shifted_rdata[7]}}, shifted_rdata[7:0]};
            3'b001: load_data = {{16{shifted_rdata[15]}}, shifted_rdata[15:0]};
            3'b010: load_data = shifted_rdata;
            3'b100: load_data = {24'b0, shifted_rdata[7:0]};
            3'b101: load_data = {16'b0, shifted_rdata[15:0]};
            default: load_data = 32'b0;
        endcase
    end

    always @* begin
        dmem_wstrb = 4'b0000;
        dmem_wdata = 32'b0;
        case (funct3)
            3'b000: begin
                dmem_wstrb = 4'b0001 << dmem_addr[1:0];
                dmem_wdata = {24'b0, rs2_data[7:0]} << ({dmem_addr[1:0], 3'b000});
            end
            3'b001: begin
                dmem_wstrb = 4'b0011 << dmem_addr[1:0];
                dmem_wdata = {16'b0, rs2_data[15:0]} << ({dmem_addr[1:0], 3'b000});
            end
            3'b010: begin
                dmem_wstrb = 4'b1111;
                dmem_wdata = rs2_data;
            end
            default: begin
                dmem_wstrb = 4'b0000;
                dmem_wdata = 32'b0;
            end
        endcase
    end

    always @* begin
        mem_misaligned = 1'b0;
        if (mem_read || mem_write) begin
            case (funct3)
                3'b001, 3'b101: mem_misaligned = dmem_addr[0];
                3'b010:         mem_misaligned = |dmem_addr[1:0];
                default:        mem_misaligned = 1'b0;
            endcase
        end
    end

    always @* begin
        case (wb_sel)
            `RV32_WB_MEM: wb_data = load_data;
            `RV32_WB_PC4: wb_data = pc_plus4;
            default:      wb_data = alu_y;
        endcase
    end

    always @(posedge clk or negedge rst_n) begin
        if (!rst_n) begin
            pc      <= RESET_PC;
            trap    <= 1'b0;
            trap_pc <= 32'b0;
        end else if (!trap) begin
            if (fault_now) begin
                trap    <= 1'b1;
                trap_pc <= pc;
            end else if (control_taken) begin
                pc <= control_target;
            end else begin
                pc <= pc_plus4;
            end
        end
    end
endmodule

verilog/verilog_sim/06_riscv/src/simple_soc.v
module simple_soc #(
    parameter MEM_WORDS = 4096,
    parameter MEM_FILE  = "src/smoke.hex"
) (
    input  wire       clk,
    input  wire       rst_n,
    output reg        tohost_valid,
    output reg [31:0] tohost_data,
    output reg [31:0] gpio_out,
    output wire       trap
);
    localparam TOHOST_ADDR = 32'h1000_0000;
    localparam GPIO_ADDR   = 32'h1000_0004;

    reg [31:0] mem [0:MEM_WORDS-1];
    integer k;

    wire [31:0] imem_addr;
    wire [31:0] imem_rdata;
    wire        dmem_valid;
    wire        dmem_we;
    wire [3:0]  dmem_wstrb;
    wire [31:0] dmem_addr;
    wire [31:0] dmem_wdata;
    reg  [31:0] dmem_rdata;
    wire [31:0] dbg_pc;
    wire [31:0] dbg_instr;
    wire [31:0] trap_pc;

    initial begin
        for (k = 0; k < MEM_WORDS; k = k + 1)
            mem[k] = 32'h0000_0013;
        $readmemh(MEM_FILE, mem);
    end

    assign imem_rdata = (imem_addr[31:2] < MEM_WORDS) ?
                        mem[imem_addr[31:2]] : 32'h0000_0013;

    always @* begin
        if (dmem_addr[31:2] < MEM_WORDS)
            dmem_rdata = mem[dmem_addr[31:2]];
        else if (dmem_addr == GPIO_ADDR)
            dmem_rdata = gpio_out;
        else
            dmem_rdata = 32'b0;
    end

    always @(posedge clk or negedge rst_n) begin
        if (!rst_n) begin
            tohost_valid <= 1'b0;
            tohost_data  <= 32'b0;
            gpio_out     <= 32'b0;
        end else if (dmem_valid && dmem_we) begin
            if (dmem_addr[31:2] < MEM_WORDS) begin
                if (dmem_wstrb[0]) mem[dmem_addr[31:2]][7:0]   <= dmem_wdata[7:0];
                if (dmem_wstrb[1]) mem[dmem_addr[31:2]][15:8]  <= dmem_wdata[15:8];
                if (dmem_wstrb[2]) mem[dmem_addr[31:2]][23:16] <= dmem_wdata[23:16];
                if (dmem_wstrb[3]) mem[dmem_addr[31:2]][31:24] <= dmem_wdata[31:24];
            end else if (dmem_addr == TOHOST_ADDR) begin
                tohost_valid <= 1'b1;
                tohost_data  <= dmem_wdata;
            end else if (dmem_addr == GPIO_ADDR) begin
                if (dmem_wstrb[0]) gpio_out[7:0]   <= dmem_wdata[7:0];
                if (dmem_wstrb[1]) gpio_out[15:8]  <= dmem_wdata[15:8];
                if (dmem_wstrb[2]) gpio_out[23:16] <= dmem_wdata[23:16];
                if (dmem_wstrb[3]) gpio_out[31:24] <= dmem_wdata[31:24];
            end
        end
    end

    rv32_core_singlecycle u_core (
        .clk(clk), .rst_n(rst_n),
        .imem_addr(imem_addr), .imem_rdata(imem_rdata),
        .dmem_valid(dmem_valid), .dmem_we(dmem_we), .dmem_wstrb(dmem_wstrb),
        .dmem_addr(dmem_addr), .dmem_wdata(dmem_wdata), .dmem_rdata(dmem_rdata),
        .trap(trap), .trap_pc(trap_pc), .dbg_pc(dbg_pc), .dbg_instr(dbg_instr)
    );
endmodule

verilog/verilog_sim/06_riscv/tb/tb_soc.v
`timescale 1ns/1ps

module tb_soc #(
    parameter MEM_FILE = "src/smoke.hex"
);
    reg clk = 1'b0;
    reg rst_n = 1'b0;
    wire tohost_valid;
    wire [31:0] tohost_data;
    wire [31:0] gpio_out;
    wire trap;
    integer cycles;

    always #5 clk = ~clk;

    simple_soc #(.MEM_FILE(MEM_FILE)) dut (
        .clk(clk), 
        .rst_n(rst_n), 
        .tohost_valid(tohost_valid),
        .tohost_data(tohost_data), 
        .gpio_out(gpio_out), 
        .trap(trap)
    );

    initial begin
        $dumpfile("wave/tb_soc.vcd");
        $dumpvars(0, tb_soc);
        repeat (5) @(posedge clk);
        rst_n <= 1'b1;

        cycles = 0;
        while (!tohost_valid && !trap && cycles < 200) begin
            @(posedge clk);
            cycles = cycles + 1;
        end

        if (trap) $fatal(1, "CPU trapped before program completion");
        if (!tohost_valid) $fatal(1, "timeout waiting for tohost");
        if (tohost_data !== 32'd1)
            $fatal(1, "program failed, tohost=%h", tohost_data);

        $display("TB_SOC PASS in %0d cycles", cycles);
        $finish;
    end
endmodule

verilog/verilog_sim/06_riscv/wave/tb_soc.vcd
$date
	Wed Aug 26 21:59:38 2026
$end
$version
	Icarus Verilog
$end
$timescale
	1ps
$end
$scope module tb_soc $end
$var wire 1 ! trap $end
$var wire 1 " tohost_valid $end
$var wire 32 # tohost_data [31:0] $end
$var wire 32 $ gpio_out [31:0] $end
$var reg 1 % clk $end
$var reg 1 & rst_n $end
$var integer 32 ' cycles [31:0] $end
$scope module dut $end
$var wire 1 % clk $end
$var wire 1 & rst_n $end
$var wire 32 ( trap_pc [31:0] $end
$var wire 1 ! trap $end
$var wire 32 ) imem_rdata [31:0] $end
$var wire 32 * imem_addr [31:0] $end
$var wire 4 + dmem_wstrb [3:0] $end
$var wire 1 , dmem_we $end
$var wire 32 - dmem_wdata [31:0] $end
$var wire 1 . dmem_valid $end
$var wire 32 / dmem_addr [31:0] $end
$var wire 32 0 dbg_pc [31:0] $end
$var wire 32 1 dbg_instr [31:0] $end
$var reg 32 2 dmem_rdata [31:0] $end
$var reg 32 3 gpio_out [31:0] $end
$var reg 32 4 tohost_data [31:0] $end
$var reg 1 " tohost_valid $end
$var integer 32 5 k [31:0] $end
$scope module u_core $end
$var wire 1 % clk $end
$var wire 1 6 control_taken $end
$var wire 32 7 dbg_instr [31:0] $end
$var wire 32 8 dbg_pc [31:0] $end
$var wire 32 9 dmem_addr [31:0] $end
$var wire 32 : dmem_rdata [31:0] $end
$var wire 1 . dmem_valid $end
$var wire 1 , dmem_we $end
$var wire 1 ; fault_now $end
$var wire 32 < imem_addr [31:0] $end
$var wire 32 = imem_rdata [31:0] $end
$var wire 1 > instr_misaligned $end
$var wire 1 ? rd_we $end
$var wire 1 & rst_n $end
$var wire 2 @ wb_sel [1:0] $end
$var wire 32 A shifted_rdata [31:0] $end
$var wire 32 B rs2_data [31:0] $end
$var wire 5 C rs2_addr [4:0] $end
$var wire 32 D rs1_data [31:0] $end
$var wire 5 E rs1_addr [4:0] $end
$var wire 1 F reg_write_dec $end
$var wire 5 G rd_addr [4:0] $end
$var wire 32 H pc_plus4 [31:0] $end
$var wire 1 I mem_write $end
$var wire 1 J mem_read $end
$var wire 32 K jump_target [31:0] $end
$var wire 1 L jump $end
$var wire 1 M jalr $end
$var wire 1 N is_lui $end
$var wire 3 O imm_sel [2:0] $end
$var wire 32 P imm [31:0] $end
$var wire 1 Q illegal_dec $end
$var wire 3 R funct3 [2:0] $end
$var wire 32 S direct_target [31:0] $end
$var wire 32 T control_target [31:0] $end
$var wire 1 U branch $end
$var wire 32 V alu_y [31:0] $end
$var wire 1 W alu_src_pc $end
$var wire 1 X alu_src_imm $end
$var wire 4 Y alu_op [3:0] $end
$var wire 32 Z alu_b [31:0] $end
$var wire 32 [ alu_a [31:0] $end
$var reg 1 \ branch_taken $end
$var reg 32 ] dmem_wdata [31:0] $end
$var reg 4 ^ dmem_wstrb [3:0] $end
$var reg 32 _ load_data [31:0] $end
$var reg 1 ` mem_misaligned $end
$var reg 32 a pc [31:0] $end
$var reg 1 ! trap $end
$var reg 32 b trap_pc [31:0] $end
$var reg 32 c wb_data [31:0] $end
$scope module u_alu $end
$var wire 32 d a [31:0] $end
$var wire 32 e b [31:0] $end
$var wire 4 f op [3:0] $end
$var reg 32 g y [31:0] $end
$upscope $end
$scope module u_decoder $end
$var wire 32 h instr [31:0] $end
$var wire 7 i opcode [6:0] $end
$var wire 7 j funct7 [6:0] $end
$var wire 3 k funct3 [2:0] $end
$var reg 4 l alu_op [3:0] $end
$var reg 1 X alu_src_imm $end
$var reg 1 W alu_src_pc $end
$var reg 1 U branch $end
$var reg 1 Q illegal $end
$var reg 3 m imm_sel [2:0] $end
$var reg 1 M jalr $end
$var reg 1 L jump $end
$var reg 1 J mem_read $end
$var reg 1 I mem_write $end
$var reg 1 F reg_write $end
$var reg 2 n wb_sel [1:0] $end
$upscope $end
$scope module u_immgen $end
$var wire 3 o imm_sel [2:0] $end
$var wire 32 p instr [31:0] $end
$var reg 32 q imm [31:0] $end
$upscope $end
$scope module u_regfile $end
$var wire 1 % clk $end
$var wire 5 r rd_addr [4:0] $end
$var wire 32 s rd_data [31:0] $end
$var wire 1 ? rd_we $end
$var wire 5 t rs1_addr [4:0] $end
$var wire 5 u rs2_addr [4:0] $end
$var wire 1 & rst_n $end
$var wire 32 v rs2_data [31:0] $end
$var wire 32 w rs1_data [31:0] $end
$var integer 32 x i [31:0] $end
$upscope $end
$upscope $end
$upscope $end
$upscope $end
$enddefinitions $end
#0
$dumpvars
b100000 x
b0 w
b0 v
b101 u
b0 t
b101 s
b1 r
b101 q
b10100000000000010010011 p
b0 o
b0 n
b0 m
b0 l
b0 k
b0 j
b10011 i
b10100000000000010010011 h
b101 g
b0 f
b101 e
b0 d
b101 c
b0 b
b0 a
0`
b1 _
b10 ^
b0 ]
1\
b0 [
b101 Z
b0 Y
1X
0W
b101 V
0U
b101 T
b101 S
b0 R
0Q
b101 P
b0 O
0N
0M
0L
b101 K
0J
0I
b100 H
b1 G
1F
b0 E
b0 D
b101 C
b0 B
b111000000000001 A
b0 @
1?
0>
b10100000000000010010011 =
b0 <
0;
b11100000000000100010011 :
b101 9
b0 8
b10100000000000010010011 7
06
b1000000000000 5
b0 4
b0 3
b11100000000000100010011 2
b10100000000000010010011 1
b0 0
b101 /
0.
b0 -
0,
b10 +
b0 *
b10100000000000010010011 )
b0 (
bx '
0&
0%
b0 $
b0 #
0"
0!
$end
#5000
b100000 x
1%
#10000
0%
#15000
b100000 x
1%
#20000
0%
#25000
b100000 x
1%
#30000
0%
#35000
b100000 x
1%
#40000
0%
#45000
1&
b100000 x
b0 '
1%
#50000
0%
#55000
b0 _
b111 c
b111 s
b1000 +
b1000 ^
b0 A
b111 /
b111 9
b111 V
b111 g
b111 Z
b111 e
b111 C
b111 u
b10 G
b10 r
b111 P
b111 q
b11100000000000100010011 1
b11100000000000100010011 7
b11100000000000100010011 )
b11100000000000100010011 =
b11100000000000100010011 h
b11100000000000100010011 p
b1011 K
b1011 T
b1000 H
b1011 S
b100 0
b100 8
b100 *
b100 <
b100 a
b1 '
1%
#60000
0%
#65000
b100011 _
b101 [
b101 d
b1100 c
b1100 s
b1100000010000000100011 A
b1100000010000000100011 2
b1100000010000000100011 :
0\
b111 -
b111 ]
b1 +
b1 ^
b1100 /
b1100 9
b1100 V
b1100 g
b101 D
b101 w
b111 B
b111 v
0X
1F
b111 Z
b111 e
b1 E
b1 t
b10 C
b10 u
b11 G
b11 r
b110011 i
b10 P
b10 q
b1000001000000110110011 1
b1000001000000110110011 7
b1000001000000110110011 )
b1000001000000110110011 =
b1000001000000110110011 h
b1000001000000110110011 p
b1010 K
b1010 T
b1100 H
b1010 S
b1000 0
b1000 8
b1000 *
b1000 <
b1000 a
b10 '
1%
#70000
0%
#75000
1.
b0 c
b0 s
b10100000000000010010011 A
b10100000000000010010011 2
b10100000000000010010011 :
b0 [
b0 d
b0 /
b0 9
b0 V
b0 g
0?
b0 Z
b0 e
b0 D
b0 w
b1100 B
b1100 v
b1100 -
b1100 ]
b1111 +
b1111 ^
b10100000000000010010011 _
b1 O
b1 m
b1 o
1,
1I
1X
0F
b0 E
b0 t
b11 C
b11 u
b0 G
b0 r
b10 R
b100011 i
b10 k
b0 P
b0 q
b1100000010000000100011 1
b1100000010000000100011 7
b1100000010000000100011 )
b1100000010000000100011 =
b1100000010000000100011 h
b1100000010000000100011 p
b1100 K
b1100 T
b10000 H
b1100 S
b1100 0
b1100 8
b1100 *
b1100 <
b1100 a
b11 '
1%
#80000
0%
#85000
1?
b0 -
b0 ]
b1111 +
b1111 ^
b1100 c
b1100 s
b0 /
b0 9
b0 V
b0 g
b0 B
b0 v
1J
b1 @
b1 n
1F
b0 O
b0 m
b0 o
0,
0I
1X
b0 Z
b0 e
b0 C
b0 u
b100 G
b100 r
b11 i
b0 P
b0 q
b1100 _
b10001000000011 1
b10001000000011 7
b10001000000011 )
b10001000000011 =
b10001000000011 h
b10001000000011 p
b1100 A
b1100 2
b1100 :
b10000 K
b10000 T
b10100 H
b10000 S
b10000 0
b10000 8
b10000 *
b10000 <
b10000 a
b100 '
1%
#90000
0%
#95000
0.
b1100 [
b1100 d
0?
b1000000000100100000001010110011 A
b1000000000100100000001010110011 2
b1000000000100100000001010110011 :
b1100 -
b1100 ]
b11000 c
b11000 s
b11000 /
b11000 9
b11000 V
b11000 g
b1100 D
b1100 w
b1100 B
b1100 v
b11 +
b11 ^
b1010110011 _
b10 O
b10 m
b10 o
1U
0J
b0 @
b0 n
0X
0F
b1100 Z
b1100 e
b11 E
b11 t
b100 C
b100 u
b0 G
b0 r
b1 R
b1100011 i
b1 k
b1 j
b100000 P
b100000 q
b10010000011001000001100011 1
b10010000011001000001100011 7
b10010000011001000001100011 )
b10010000011001000001100011 =
b10010000011001000001100011 h
b10010000011001000001100011 p
b110100 K
b110100 T
b11000 H
b110100 S
b10100 0
b10100 8
b10100 *
b10100 <
b10100 a
b101 '
1%
#100000
0%
#105000
b0 A
b11100000000000100010011 2
b11100000000000100010011 :
1?
b101 Z
b101 e
b111 c
b111 s
b111 /
b111 9
b111 V
b111 g
b101 B
b101 v
b101000000000000000000000000 -
b101000000000000000000000000 ]
b1000 +
b1000 ^
b0 _
0\
b1 Y
b1 f
b1 l
1F
b0 O
b0 m
b0 o
0U
b100 E
b100 t
b1 C
b1 u
b101 G
b101 r
b0 R
b110011 i
b0 k
b100000 j
b10000000001 P
b10000000001 q
b1000000000100100000001010110011 1
b1000000000100100000001010110011 7
b1000000000100100000001010110011 )
b1000000000100100000001010110011 =
b1000000000100100000001010110011 h
b1000000000100100000001010110011 p
b10000011001 K
b10000011001 T
b11100 H
b10000011001 S
b11000 0
b11000 8
b11000 *
b11000 <
b11000 a
b110 '
1%
#110000
0%
#115000
b0 _
b0 [
b0 d
b111 c
b111 s
b0 A
b11100000000000100010011 2
b11100000000000100010011 :
1\
b0 -
b0 ]
b1000 +
b1000 ^
b111 Z
b111 e
b111 /
b111 9
b111 V
b111 g
b0 D
b0 w
b0 B
b0 v
1X
b0 Y
b0 f
b0 l
1F
b0 E
b0 t
b111 C
b111 u
b110 G
b110 r
b10011 i
b0 j
b111 P
b111 q
b11100000000001100010011 1
b11100000000001100010011 7
b11100000000001100010011 )
b11100000000001100010011 =
b11100000000001100010011 h
b11100000000001100010011 p
b100011 K
b100011 T
b100000 H
b100011 S
b11100 0
b11100 8
b11100 *
b11100 <
b11100 a
b111 '
1%
#120000
0%
#125000
b1100000010000000100011 2
b1100000010000000100011 :
b110000 _
b111 [
b111 d
0?
b1110 c
b1110 s
b110000 A
b1110000000000000000 -
b1110000000000000000 ]
b1110 /
b1110 9
b1110 V
b1110 g
b111 D
b111 w
b111 B
b111 v
b1100 +
b1100 ^
0\
b10 O
b10 m
b10 o
1U
0X
0F
b111 Z
b111 e
b101 E
b101 t
b110 C
b110 u
b10100 G
b10100 r
b1 R
b1100011 i
b1 k
b10100 P
b10100 q
b11000101001101001100011 1
b11000101001101001100011 7
b11000101001101001100011 )
b11000101001101001100011 =
b11000101001101001100011 h
b11000101001101001100011 p
b110100 K
b110100 T
b100100 H
b110100 S
b100000 0
b100000 8
b100000 *
b100000 <
b100000 a
b1000 '
1%
#130000
0%
